{
  "id": "28w7",
  "slug": "sam3-an",
  "name": "Sam3 AN",
  "version": "V1.1.0",
  "description": {
    "en": "基于Meta sam3模型的数据标注工具",
    "cn": "基于Meta sam3模型的数据标注工具"
  },
  "stars": 72,
  "updated_at": "2026-04-26T09:53:50Z",
  "icon": "",
  "collections_tags": [
    "linuxdo"
  ],
  "download_count": 0,
  "download_url": "https://github.com/fivif/Sam3-AN/releases/tag/V1.1.0",
  "homepage": "https://github.com/fivif/sam3-an",
  "category": "tool",
  "linuxdo": {
    "post_url": "https://linux.do/t/topic/1306118",
    "author_username": "fivif",
    "author_avatar_url": "https://cdn.linux.do/user_avatar/linux.do/fivif/48/1274003_2.png"
  },
  "source": "linuxdo",
  "release_url": "https://github.com/fivif/Sam3-AN/releases/tag/V1.1.0",
  "windows_assets": "Sam3.AN.zip"
}
