{
  "id": "b337",
  "slug": "wazuh",
  "name": "wazuh",
  "version": "4.14.5",
  "description": {
    "en": "Wazuh - The Open Source Security Platform. Unified XDR and SIEM protection for endpoints and cloud workloads.",
    "cn": "Wazuh 安全平台  "
  },
  "source": "github-trending",
  "stars": 0,
  "updated_at": "2026-04-23T11:46:46Z",
  "icon": "",
  "collections_tags": [
    "c++"
  ],
  "download_count": 0,
  "download_url": "",
  "homepage": "https://github.com/wazuh/wazuh",
  "category": "tool",
  "windows_assets": [],
  "release_url": "https://github.com/wazuh/wazuh/releases/tag/v4.14.5"
}