[
  {
    "id": "a3cf",
    "slug": "obsidian",
    "name": "Obsidian",
    "version": "1.10.6",
    "description": {
      "en": "This is a powerful knowledge management and note-taking application.",
      "cn": "这是一个强大的知识管理和笔记应用。"
    }
  },
  {
    "id": "b7e2",
    "slug": "vscode",
    "name": "Visual Studio Code",
    "version": "1.107.0",
    "description": {
      "en": "This is a code editor from Microsoft.",
      "cn": "这是微软出品的代码编辑器。"
    }
  },
  {
    "id": "c8f3",
    "slug": "pixpin",
    "name": "PixPin",
    "version": "2.2.4.1",
    "description": {
      "en": "Screenshot, screen recording, OCR - a fast and flexible tool.",
      "cn": "截图、录屏、OCR - 一款快速灵活的工具。"
    }
  },
  {
    "id": "d9f4",
    "slug": "bulk-crap-uninstaller",
    "name": "Bulk Crap Uninstaller",
    "version": "5.9",
    "description": {
      "en": "Remove large amounts of unwanted applications quickly.",
      "cn": "快速卸载大量不需要的应用程序。"
    }
  },
  {
    "id": "e5g5",
    "slug": "super-productivity",
    "name": "Super Productivity",
    "version": "16.6.0",
    "description": {
      "en": "A powerful and flexible To-Do and time management application, easy to use.",
      "cn": "功能非常强大的ToDo和时间管理应用，用起来非常简单"
    }
  }
]